mizmerge/__init__.py
mizmerge/mizmerge.py
mizmerge/version
mizmerge/modsupport/__init__.py
mizmerge/modsupport/modsupport.py
mizmerge/pydcs_extensions/__init__.py
mizmerge/pydcs_extensions/weapon_injector.py
mizmerge/pydcs_extensions/a4ec/__init__.py
mizmerge/pydcs_extensions/a4ec/a4ec.py
dcs_mizmerge-0.0.4.dist-info/LICENSE
dcs_mizmerge-0.0.4.dist-info/METADATA
dcs_mizmerge-0.0.4.dist-info/WHEEL
dcs_mizmerge-0.0.4.dist-info/dependency_links.txt
dcs_mizmerge-0.0.4.dist-info/entry_points.txt
dcs_mizmerge-0.0.4.dist-info/top_level.txt
dcs_mizmerge-0.0.4.dist-info/RECORD
