Metadata-Version: 2.1
Name: dcs-mizmerge
Version: 0.0.4
Summary: Python tool for merging DCS mission files
Home-page: https://github.com/walterroach
Author: Walter Haynie
License: UNKNOWN
Platform: UNKNOWN
Classifier: Programming Language :: Python :: 3
Classifier: Operating System :: OS Independent
Requires-Python: >=3.10
License-File: LICENSE
Requires-Dist: pyproj
Requires-Dist: pydcs (>=0.13.0)
